calculator_mcp/__init__.py
calculator_mcp/__main__.py
mark_anthony_calculator_mcp-1.0.21.dist-info/METADATA
mark_anthony_calculator_mcp-1.0.21.dist-info/WHEEL
mark_anthony_calculator_mcp-1.0.21.dist-info/entry_points.txt
mark_anthony_calculator_mcp-1.0.21.dist-info/licenses/LICENSE
mark_anthony_calculator_mcp-1.0.21.dist-info/RECORD
