Metadata-Version: 2.4
Name: mark-anthony-calculator-mcp
Version: 1.0.21
Summary: A Model Context Protocol server for calculator operations
Project-URL: Homepage, https://github.com/yourusername/calculator-mcp
Project-URL: Repository, https://github.com/yourusername/calculator-mcp
Author: Your Name
License: MIT
License-File: LICENSE
Keywords: calculator,mcp,model-context-protocol
Classifier: Development Status :: 4 - Beta
Classifier: Intended Audience :: Developers
Classifier: License :: OSI Approved :: MIT License
Classifier: Programming Language :: Python :: 3
Classifier: Programming Language :: Python :: 3.10
Classifier: Programming Language :: Python :: 3.11
Classifier: Programming Language :: Python :: 3.12
Requires-Python: >=3.10
Requires-Dist: mcp>=0.9.0
Provides-Extra: dev
Requires-Dist: black>=23.0.0; extra == 'dev'
Requires-Dist: pytest>=7.0.0; extra == 'dev'
Requires-Dist: ruff>=0.1.0; extra == 'dev'
